mr/blocks/__init__.py
mr/blocks/conv_block.py
mr/blocks/res_block.py
mr/datamodules/__init__.py
mr/datamodules/base_datamodule.py
mr/datamodules/celeba_datamodule.py
mr/models/__init__.py
mr/models/base_module.py
mr/models/cycle_gan/__init__.py
mr/models/cycle_gan/components.py
mr/models/cycle_gan/cycle_gan_module.py
mr/models/wavenet/__init__.py
mr/models/wavenet/components.py
mr/models/wavenet/wavenet_module.py
mr/utils/__init__.py
mr/utils/metric_calculator.py
mr/utils/parameters_counter.py
mr/utils/randomizer.py
mtr-0.0.1.dist-info/LICENSE
mtr-0.0.1.dist-info/METADATA
mtr-0.0.1.dist-info/WHEEL
mtr-0.0.1.dist-info/top_level.txt
mtr-0.0.1.dist-info/RECORD
