Metadata-Version: 2.1
Name: mtr
Version: 0.0.1
Summary: mr
Home-page: UNKNOWN
Author: sergevkim
License: UNKNOWN
Platform: UNKNOWN
Classifier: Programming Language :: Python :: 3
Classifier: License :: OSI Approved :: MIT License
Classifier: Operating System :: OS Independent
Requires-Python: >=3.7
License-File: LICENSE
Requires-Dist: albumentations
Requires-Dist: einops
Requires-Dist: torch (>=1.8.0)
Requires-Dist: wandb
